Metadata-Version: 2.1
Name: treesak
Version: 1.54.0
Summary: BioSAK
Home-page: https://github.com/songweizhi/TreeSAK
Author: Weizhi Song
Author-email: songwz03@gmail.com
License: GPL3+
Keywords: Bioinformatics
License-File: LICENSE
Requires-Dist: biopython
Requires-Dist: matplotlib
Requires-Dist: numpy
Requires-Dist: scipy
Requires-Dist: itolapi
Requires-Dist: networkx
Requires-Dist: seaborn
Requires-Dist: lxml
Requires-Dist: beautifulsoup4
Requires-Dist: ete3
Requires-Dist: arviz
Requires-Dist: plotly
Requires-Dist: kaleido
Requires-Dist: PyPDF3
Requires-Dist: dendropy
